nearai/__init__.py
nearai/__main__.py
nearai/agent_creator.py
nearai/banners.py
nearai/benchmark.py
nearai/cli.py
nearai/cli_help.py
nearai/cli_helpers.py
nearai/config.py
nearai/dataset.py
nearai/delegation.py
nearai/evaluation.py
nearai/hub.py
nearai/jobs.py
nearai/lib.py
nearai/log.py
nearai/login.py
nearai/model.py
nearai/registry.py
nearai/streamlit_inspect.py
nearai/tensorboard_feed.py
nearai/agents/__init__.py
nearai/agents/agent.py
nearai/agents/analytics.py
nearai/agents/environment.py
nearai/agents/local_runner.py
nearai/agents/template.py.txt
nearai/agents/tool_json_helper.py
nearai/agents/tool_registry.py
nearai/agents/models/tool_definition.py
nearai/assets/auth_capture.html
nearai/assets/auth_complete.html
nearai/aws_runner/partial_near_client.py
nearai/aws_runner/service.py
nearai/clients/debug_client.py
nearai/clients/lambda_client.py
nearai/openapi_client/__init__.py
nearai/openapi_client/api_client.py
nearai/openapi_client/api_response.py
nearai/openapi_client/configuration.py
nearai/openapi_client/exceptions.py
nearai/openapi_client/py.typed
nearai/openapi_client/rest.py
nearai/openapi_client/api/__init__.py
nearai/openapi_client/api/agents_api.py
nearai/openapi_client/api/agents_assistants_api.py
nearai/openapi_client/api/assistants_api.py
nearai/openapi_client/api/benchmark_api.py
nearai/openapi_client/api/default_api.py
nearai/openapi_client/api/delegation_api.py
nearai/openapi_client/api/evaluation_api.py
nearai/openapi_client/api/hub_secrets_api.py
nearai/openapi_client/api/jobs_api.py
nearai/openapi_client/api/logs_api.py
nearai/openapi_client/api/permissions_api.py
nearai/openapi_client/api/registry_api.py
nearai/openapi_client/api/stars_api.py
nearai/openapi_client/models/__init__.py
nearai/openapi_client/models/benchmark_output.py
nearai/openapi_client/models/benchmark_result_output.py
nearai/openapi_client/models/body_add_job_v1_jobs_add_job_post.py
nearai/openapi_client/models/body_download_file_v1_registry_download_file_post.py
nearai-0.1.19.dist-info/METADATA
nearai-0.1.19.dist-info/WHEEL
nearai-0.1.19.dist-info/entry_points.txt
nearai-0.1.19.dist-info/licenses/LICENSE
nearai-0.1.19.dist-info/RECORD
